exercicio_criacao_pacote/__init__.py
exercicio_criacao_pacote/file1_name.py
exercicio_criacao_pacote/file2_name.py
exercicio_criacao_pacote-0.0.1.dist-info/METADATA
exercicio_criacao_pacote-0.0.1.dist-info/WHEEL
exercicio_criacao_pacote-0.0.1.dist-info/top_level.txt
exercicio_criacao_pacote-0.0.1.dist-info/RECORD
