Metadata-Version: 2.1
Name: exercicio-criacao-pacote
Version: 0.0.1
Summary: Criação do meu primeiro pacote
Home-page: https://github.com/MichelleMapelli?tab=repositories
Author: Michelle Trigueiro
Author-email: mi.mapelli@gmail.com
License: UNKNOWN
Platform: UNKNOWN
Requires-Python: >=3.8
